examples/.env.example
examples/README.md
examples/getting_started_google_ai.py
examples/getting_started_vertex_ai.py
examples/simple_embeddings_test.py
examples/simple_streaming_test.py
examples/simple_test.py
examples/trace_visualization_example.py
revenium_middleware_google/__init__.py
revenium_middleware_google/common/__init__.py
revenium_middleware_google/common/exceptions.py
revenium_middleware_google/common/protocols.py
revenium_middleware_google/common/trace_fields.py
revenium_middleware_google/common/types.py
revenium_middleware_google/common/url_standardization.py
revenium_middleware_google/common/utils.py
revenium_middleware_google/google_ai/__init__.py
revenium_middleware_google/google_ai/middleware.py
revenium_middleware_google/google_ai/provider.py
revenium_middleware_google/vertex_ai/__init__.py
revenium_middleware_google/vertex_ai/middleware.py
revenium_middleware_google/vertex_ai/provider.py
revenium_middleware_google-0.2.0.dist-info/licenses/LICENSE
revenium_middleware_google-0.2.0.dist-info/METADATA
revenium_middleware_google-0.2.0.dist-info/WHEEL
revenium_middleware_google-0.2.0.dist-info/top_level.txt
revenium_middleware_google-0.2.0.dist-info/RECORD
