Metadata-Version: 2.4
Name: revenium-middleware-google
Version: 0.2.0
Summary: A Python library that meters Google AI API usage to Revenium with support for both Gemini Developer API and Vertex AI.
Author-email: Revenium <support@revenium.io>
License-Expression: MIT
Project-URL: Homepage, https://github.com/revenium/revenium-middleware-google-python
Project-URL: Bug Tracker, https://github.com/revenium/revenium-middleware-google-python/issues
Project-URL: Documentation, https://github.com/revenium/revenium-middleware-google-python/blob/main/README.md
Keywords: google,gemini,vertex-ai,middleware,logging,token-usage,metering,revenium,ai,llm
Classifier: Development Status :: 5 - Production/Stable
Classifier: Programming Language :: Python :: 3
Classifier: Programming Language :: Python :: 3.8
Classifier: Programming Language :: Python :: 3.9
Classifier: Programming Language :: Python :: 3.10
Classifier: Programming Language :: Python :: 3.11
Classifier: Programming Language :: Python :: 3.12
Classifier: Operating System :: OS Independent
Classifier: Intended Audience :: Developers
Classifier: Topic :: Software Development :: Libraries :: Python Modules
Requires-Python: >=3.8
License-File: LICENSE
Requires-Dist: wrapt
Requires-Dist: revenium_middleware>=0.4.0
Provides-Extra: genai
Requires-Dist: google-genai>=0.1.0; extra == "genai"
Requires-Dist: python-dotenv; extra == "genai"
Provides-Extra: vertex
Requires-Dist: vertexai>=1.0.0; extra == "vertex"
Requires-Dist: python-dotenv; extra == "vertex"
Provides-Extra: all
Requires-Dist: google-genai>=0.1.0; extra == "all"
Requires-Dist: vertexai>=1.0.0; extra == "all"
Requires-Dist: python-dotenv; extra == "all"
Provides-Extra: examples
Requires-Dist: python-dotenv; extra == "examples"
Provides-Extra: dev
Requires-Dist: pytest>=7.0.0; extra == "dev"
Requires-Dist: pytest-cov; extra == "dev"
Requires-Dist: flake8; extra == "dev"
Requires-Dist: black; extra == "dev"
Requires-Dist: mypy; extra == "dev"
Requires-Dist: freezegun; extra == "dev"
Requires-Dist: python-dotenv; extra == "dev"
Dynamic: license-file
